{
  "type": "lab",
  "title": "Adjusting for Chance in Clustering Performance Evaluation",
  "description": "This lab explores the impact of uniformly-distributed random labeling on the behavior of some clustering evaluation metrics. Clustering algorithms are fundamentally unsupervised learning methods and evaluation metrics that leverage \"supervised\" ground truth information to quantify the quality of the resulting clusters. However, non-adjusted clustering evaluation metrics can be misleading as they output large values for fine-grained labelings, which can be totally random. Therefore, only adjusted measures can be safely used as a consensus index to evaluate the average stability of clustering algorithms for a given value of k on various overlapping sub-samples of the dataset.",
  "difficulty": "Beginner",
  "time": 25,
  "hidden": false,
  "fee_type": "free",
  "details": {
    "steps": [
      {
        "title": "Defining the List of Metrics to Evaluate",
        "text": "step1.md",
        "verify": [
          {
            "name": "Test the completion of step 1",
            "file": "verify1.sh",
            "hint": "You need to practice coding in plot-adjusted-for-chance-measures.ipynb",
            "timeout": 0,
            "showstderr": false
          }
        ],
        "skills": []
      },
      {
        "title": "Experiment 1 - Fixed Ground Truth Labels and Growing Number of Clusters",
        "text": "step2.md",
        "verify": [
          {
            "name": "Test the completion of step 2",
            "file": "verify2.sh",
            "hint": "You need to practice coding in plot-adjusted-for-chance-measures.ipynb",
            "timeout": 0,
            "showstderr": false
          }
        ],
        "skills": []
      },
      {
        "title": "Plotting Experiment 1 Results",
        "text": "step3.md",
        "verify": [
          {
            "name": "Test the completion of step 3",
            "file": "verify3.sh",
            "hint": "You need to practice coding in plot-adjusted-for-chance-measures.ipynb",
            "timeout": 0,
            "showstderr": false
          }
        ],
        "skills": []
      },
      {
        "title": "Experiment 2 - Varying Number of Classes and Clusters",
        "text": "step4.md",
        "verify": [
          {
            "name": "Test the completion of step 4",
            "file": "verify4.sh",
            "hint": "You need to practice coding in plot-adjusted-for-chance-measures.ipynb",
            "timeout": 0,
            "showstderr": false
          }
        ],
        "skills": []
      },
      {
        "title": "Plotting Experiment 2 Results",
        "text": "step5.md",
        "verify": [
          {
            "name": "Test the completion of step 5",
            "file": "verify5.sh",
            "hint": "You need to practice coding in plot-adjusted-for-chance-measures.ipynb",
            "timeout": 0,
            "showstderr": false
          }
        ],
        "skills": []
      }
    ],
    "intro": {
      "text": "intro.md",
      "background": "setup.sh"
    },
    "finish": {
      "text": "finish.md"
    },
    "assets": {
      "host01": [
        {
          "file": "plot-adjusted-for-chance-measures.ipynb",
          "target": "/home/labex/project",
          "chmod": "ugo+rwx"
        }
      ]
    }
  },
  "backend": {
    "imageid": "webide-ubuntu:2204"
  },
  "contributors": ["huhuhang"],
  "license": {
    "name": "BSD 3-Clause",
    "url": "https://github.com/scikit-learn/scikit-learn/tree/main/LICENSE",
    "repo": "https://github.com/scikit-learn/scikit-learn"
  }
}
