{
  "$schema": "https://cdn.jsdelivr.net/gh/labex-labs/schema/index.json",
  "type": "lab",
  "title": "Robust Covariance Estimation and Mahalanobis Distances Relevance",
  "description": "In this lab, we will explore the use of robust covariance estimation with Mahalanobis distances on Gaussian distributed data. Mahalanobis distance is a measure of the distance between a point and a distribution. It is defined as the distance between a point and the mean of the distribution, scaled by the inverse of the covariance matrix of the distribution. For Gaussian distributed data, the Mahalanobis distance can be used to compute the distance of an observation to the mode of the distribution. We will compare the performance of the Minimum Covariance Determinant (MCD) estimator, a robust estimator of covariance, with the standard covariance Maximum Likelihood Estimator (MLE) in calculating the Mahalanobis distances of a contaminated dataset.",
  "meta": {
    "title": "Robust Covariance Estimation | Mahalanobis Distance | Gaussian Data",
    "description": "Explore robust covariance estimation using Mahalanobis distance on Gaussian distributed data, compare MCD and MLE estimators for contaminated datasets.",
    "keywords": "Robust Covariance Estimation, Mahalanobis Distance, Gaussian Data, MCD Estimator, MLE Estimator"
  },
  "difficulty": "Beginner",
  "time": 20,
  "hidden": false,
  "fee_type": "free",
  "show_in_tutorial": true,
  "details": {
    "steps": [
      {
        "title": "Generate Data",
        "text": "en/step1.md",
        "verify": [
          {
            "name": "This step has no verification at the moment",
            "file": "verify1-1.sh",
            "hint": "This step has no verification at the moment"
          }
        ],
        "skills": ["ml/sklearn"]
      },
      {
        "title": "Fit MCD and MLE Covariance Estimators to Data",
        "text": "en/step2.md",
        "verify": [
          {
            "name": "This step has no verification at the moment",
            "file": "verify2-1.sh",
            "hint": "This step has no verification at the moment"
          }
        ],
        "skills": ["ml/sklearn", "sklearn/covariance"]
      },
      {
        "title": "Plot Contours of Mahalanobis Distances",
        "text": "en/step3.md",
        "verify": [
          {
            "name": "This step has no verification at the moment",
            "file": "verify3-1.sh",
            "hint": "This step has no verification at the moment"
          }
        ],
        "skills": ["ml/sklearn"]
      },
      {
        "title": "Compare MLE and MCD Mahalanobis Distances",
        "text": "en/step4.md",
        "verify": [
          {
            "name": "This step has no verification at the moment",
            "file": "verify4-1.sh",
            "hint": "This step has no verification at the moment"
          }
        ],
        "skills": ["ml/sklearn"]
      }
    ],
    "intro": {
      "text": "en/intro.md",
      "title": "Introduction",
      "background": "setup.sh"
    },
    "finish": {
      "text": "en/finish.md",
      "title": "Summary"
    },
    "assets": {
      "host01": [
        {
          "file": "plot-mahalanobis-distances.ipynb",
          "target": "/home/labex/project",
          "chmod": "ugo+rwx"
        }
      ]
    }
  },
  "backend": {
    "imageid": "jupyter-ubuntu:2204"
  },
  "contributors": [],
  "license": {
    "name": "BSD 3-Clause",
    "url": "https://github.com/scikit-learn/scikit-learn/tree/main/LICENSE",
    "repo": "https://github.com/scikit-learn/scikit-learn"
  },
  "i18n": [
    {
      "lang": "zh",
      "title": "稳健协方差估计与马氏距离的相关性",
      "description": "在本实验中，我们将探索在高斯分布数据上使用马氏距离进行稳健协方差估计。马氏距离是衡量一个点与一个分布之间距离的指标。它被定义为一个点与分布均值之间的距离，并通过分布协方差矩阵的逆进行缩放。对于高斯分布的数据，马氏距离可用于计算一个观测值到分布众数的距离。我们将在计算受污染数据集的马氏距离时，比较协方差的稳健估计器——最小协方差行列式（MCD）估计器与标准协方差最大似然估计器（MLE）的性能。",
      "meta": {
        "title": "稳健协方差估计 | 马氏距离 | 高斯数据",
        "description": "探索在高斯分布数据上使用马氏距离进行稳健协方差估计，比较受污染数据集的 MCD 和 MLE 估计器。",
        "keywords": "稳健协方差估计，马氏距离，高斯数据，MCD 估计器，MLE 估计器"
      },
      "details": {
        "steps": [
          {
            "title": "生成数据",
            "text": "zh/step1.md",
            "verify": [
              {
                "name": "此步骤目前没有验证",
                "file": "verify1-1.sh",
                "hint": "此步骤目前没有验证"
              }
            ]
          },
          {
            "title": "将 MCD 和 MLE 协方差估计器应用于数据",
            "text": "zh/step2.md",
            "verify": [
              {
                "name": "此步骤目前没有验证",
                "file": "verify2-1.sh",
                "hint": "此步骤目前没有验证"
              }
            ]
          },
          {
            "title": "绘制马氏距离的等高线",
            "text": "zh/step3.md",
            "verify": [
              {
                "name": "此步骤目前没有验证",
                "file": "verify3-1.sh",
                "hint": "此步骤目前没有验证"
              }
            ]
          },
          {
            "title": "比较 MLE 和 MCD 的马氏距离",
            "text": "zh/step4.md",
            "verify": [
              {
                "name": "此步骤目前没有验证",
                "file": "verify4-1.sh",
                "hint": "此步骤目前没有验证"
              }
            ]
          }
        ],
        "intro": {
          "text": "zh/intro.md",
          "title": "介绍"
        },
        "finish": {
          "text": "zh/finish.md",
          "title": "总结"
        }
      }
    },
    {
      "lang": "es",
      "title": "Relevancia de la estimación robusta de covarianza y las distancias de Mahalanobis",
      "description": "En este laboratorio, exploraremos el uso de la estimación robusta de covarianza con distancias de Mahalanobis en datos distribuidos gaussianamente. La distancia de Mahalanobis es una medida de la distancia entre un punto y una distribución. Se define como la distancia entre un punto y la media de la distribución, escalada por la inversa de la matriz de covarianza de la distribución. Para datos distribuidos gaussianamente, la distancia de Mahalanobis se puede utilizar para calcular la distancia de una observación al modo de la distribución. Compararemos el rendimiento del estimador de Determinante de Covarianza Mínima (MCD), un estimador robusto de covarianza, con el estimador estándar de covarianza de Máxima Verosimilitud (MLE) al calcular las distancias de Mahalanobis de un conjunto de datos contaminado.",
      "meta": {
        "title": "Estimación robusta de covarianza | Distancia de Mahalanobis | Datos gaussianos",
        "description": "Explore la estimación robusta de covarianza utilizando la distancia de Mahalanobis en datos distribuidos gaussianamente, compare los estimadores MCD y MLE para conjuntos de datos contaminados.",
        "keywords": "Estimación robusta de covarianza, Distancia de Mahalanobis, Datos gaussianos, Estimador MCD, Estimador MLE"
      },
      "details": {
        "steps": [
          {
            "title": "Generar datos",
            "text": "es/step1.md",
            "verify": [
              {
                "name": "Este paso no tiene verificación en este momento",
                "file": "verify1-1.sh",
                "hint": "Este paso no tiene verificación en este momento"
              }
            ]
          },
          {
            "title": "Ajustar los estimadores de covarianza MCD y MLE a los datos",
            "text": "es/step2.md",
            "verify": [
              {
                "name": "Este paso no tiene verificación en este momento",
                "file": "verify2-1.sh",
                "hint": "Este paso no tiene verificación en este momento"
              }
            ]
          },
          {
            "title": "Trazar los contornos de las distancias de Mahalanobis",
            "text": "es/step3.md",
            "verify": [
              {
                "name": "Este paso no tiene verificación en este momento",
                "file": "verify3-1.sh",
                "hint": "Este paso no tiene verificación en este momento"
              }
            ]
          },
          {
            "title": "Comparar las distancias de Mahalanobis de MLE y MCD",
            "text": "es/step4.md",
            "verify": [
              {
                "name": "Este paso no tiene verificación en este momento",
                "file": "verify4-1.sh",
                "hint": "Este paso no tiene verificación en este momento"
              }
            ]
          }
        ],
        "intro": {
          "text": "es/intro.md",
          "title": "Introducción"
        },
        "finish": {
          "text": "es/finish.md",
          "title": "Resumen"
        }
      }
    },
    {
      "lang": "fr",
      "title": "Estimation de covariance robuste et pertinence des distances de Mahalanobis",
      "description": "Dans ce laboratoire, nous explorerons l'utilisation d'une estimation de covariance robuste avec des distances de Mahalanobis sur des données distribuées selon une loi normale. La distance de Mahalanobis est une mesure de la distance entre un point et une distribution. Elle est définie comme la distance entre un point et la moyenne de la distribution, mise à l'échelle par l'inverse de la matrice de covariance de la distribution. Pour des données distribuées selon une loi normale, la distance de Mahalanobis peut être utilisée pour calculer la distance d'une observation au mode de la distribution. Nous comparerons les performances de l'estimateur de déterminant de covariance minimale (MCD), un estimateur robuste de covariance, avec l'estimateur de covariance maximum de vraisemblance standard (MLE) dans le calcul des distances de Mahalanobis d'un ensemble de données contaminé.",
      "meta": {
        "title": "Estimation de covariance robuste | Distance de Mahalanobis | Données gaussiennes",
        "description": "Explorez l'estimation de covariance robuste en utilisant la distance de Mahalanobis sur des données distribuées selon une loi normale, comparez les estimateurs MCD et MLE pour des ensembles de données contaminés.",
        "keywords": "Estimation de covariance robuste, Distance de Mahalanobis, Données gaussiennes, Estimateur MCD, Estimateur MLE"
      },
      "details": {
        "steps": [
          {
            "title": "Générer des données",
            "text": "fr/step1.md",
            "verify": [
              {
                "name": "Cette étape n'a pas de vérification pour le moment",
                "file": "verify1-1.sh",
                "hint": "Cette étape n'a pas de vérification pour le moment"
              }
            ]
          },
          {
            "title": "Ajuster les estimateurs de covariance MCD et MLE aux données",
            "text": "fr/step2.md",
            "verify": [
              {
                "name": "Cette étape n'a pas de vérification pour le moment",
                "file": "verify2-1.sh",
                "hint": "Cette étape n'a pas de vérification pour le moment"
              }
            ]
          },
          {
            "title": "Tracer les contours des distances de Mahalanobis",
            "text": "fr/step3.md",
            "verify": [
              {
                "name": "Cette étape n'a pas de vérification pour le moment",
                "file": "verify3-1.sh",
                "hint": "Cette étape n'a pas de vérification pour le moment"
              }
            ]
          },
          {
            "title": "Comparer les distances de Mahalanobis MLE et MCD",
            "text": "fr/step4.md",
            "verify": [
              {
                "name": "Cette étape n'a pas de vérification pour le moment",
                "file": "verify4-1.sh",
                "hint": "Cette étape n'a pas de vérification pour le moment"
              }
            ]
          }
        ],
        "intro": {
          "text": "fr/intro.md",
          "title": "Introduction"
        },
        "finish": {
          "text": "fr/finish.md",
          "title": "Résumé"
        }
      }
    },
    {
      "lang": "de",
      "title": "Robuste Kovarianzschätzung und Relevanz von Mahalanobis-Distanzen",
      "description": "In diesem Lab werden wir die Verwendung der robusten Kovarianzschätzung mit Mahalanobis-Distanzen für gaussverteiltes Daten untersuchen. Die Mahalanobis-Distanz misst die Entfernung zwischen einem Punkt und einer Verteilung. Sie wird definiert als die Entfernung zwischen einem Punkt und dem Mittelwert der Verteilung, skaliert mit der Inverse der Kovarianzmatrix der Verteilung. Für gaussverteiltes Daten kann die Mahalanobis-Distanz verwendet werden, um die Entfernung einer Beobachtung zum Modalwert der Verteilung zu berechnen. Wir werden die Leistung des Minimum Covariance Determinant (MCD)-Schätzers, eines robusten Kovarianzschätzers, mit dem Standard-Kovarianz-Maximum Likelihood Estimator (MLE) bei der Berechnung der Mahalanobis-Distanzen eines kontaminierten Datensatzes vergleichen.",
      "meta": {
        "title": "Robuste Kovarianzschätzung | Mahalanobis-Distanz | Gauss-Daten",
        "description": "Entdecken Sie die robuste Kovarianzschätzung mit Mahalanobis-Distanz für gaussverteiltes Daten und vergleichen Sie MCD- und MLE-Schätzer für kontaminierte Datensätze.",
        "keywords": "Robuste Kovarianzschätzung, Mahalanobis-Distanz, Gauss-Daten, MCD-Schätzer, MLE-Schätzer"
      },
      "details": {
        "steps": [
          {
            "title": "Daten generieren",
            "text": "de/step1.md",
            "verify": [
              {
                "name": "Dieser Schritt hat momentan keine Verifizierung",
                "file": "verify1-1.sh",
                "hint": "Dieser Schritt hat momentan keine Verifizierung"
              }
            ]
          },
          {
            "title": "MCD- und MLE-Kovarianzschätzer an die Daten anpassen",
            "text": "de/step2.md",
            "verify": [
              {
                "name": "Dieser Schritt hat momentan keine Verifizierung",
                "file": "verify2-1.sh",
                "hint": "Dieser Schritt hat momentan keine Verifizierung"
              }
            ]
          },
          {
            "title": "Mahalanobis-Distanzen konturieren",
            "text": "de/step3.md",
            "verify": [
              {
                "name": "Dieser Schritt hat momentan keine Verifizierung",
                "file": "verify3-1.sh",
                "hint": "Dieser Schritt hat momentan keine Verifizierung"
              }
            ]
          },
          {
            "title": "Vergleiche MLE- und MCD-Mahalanobis-Distanzen",
            "text": "de/step4.md",
            "verify": [
              {
                "name": "Dieser Schritt hat momentan keine Verifizierung",
                "file": "verify4-1.sh",
                "hint": "Dieser Schritt hat momentan keine Verifizierung"
              }
            ]
          }
        ],
        "intro": {
          "text": "de/intro.md",
          "title": "Einführung"
        },
        "finish": {
          "text": "de/finish.md",
          "title": "Zusammenfassung"
        }
      }
    },
    {
      "lang": "ja",
      "title": "頑健な共分散推定とマハラノビス距離の関連性",
      "description": "この実験では、ガウス分布データに対してマハラノビス距離を用いた頑健な共分散推定の使用方法を探ります。マハラノビス距離は、点と分布の間の距離の尺度です。これは、点と分布の平均の間の距離を、分布の共分散行列の逆行列でスケーリングしたものとして定義されます。ガウス分布データの場合、マハラノビス距離は、観測値が分布の最頻値までの距離を計算するために使用できます。汚染されたデータセットのマハラノビス距離を計算する際の、共分散の頑健推定器である最小共分散決定（MCD）推定器と、標準の共分散最大尤度推定器（MLE）の性能を比較します。",
      "meta": {
        "title": "頑健な共分散推定 | マハラノビス距離 | ガウスデータ",
        "description": "ガウス分布データに対してマハラノビス距離を使用した頑健な共分散推定を探り、汚染されたデータセットに対する MCD と MLE 推定器を比較します。",
        "keywords": "頑健な共分散推定，マハラノビス距離，ガウスデータ，MCD 推定器，MLE 推定器"
      },
      "details": {
        "steps": [
          {
            "title": "データを生成する",
            "text": "ja/step1.md",
            "verify": [
              {
                "name": "このステップには現在、検証はありません",
                "file": "verify1-1.sh",
                "hint": "このステップには現在、検証はありません"
              }
            ]
          },
          {
            "title": "データに MCD と MLE 共分散推定器をフィットさせる",
            "text": "ja/step2.md",
            "verify": [
              {
                "name": "このステップには現在、検証はありません",
                "file": "verify2-1.sh",
                "hint": "このステップには現在、検証はありません"
              }
            ]
          },
          {
            "title": "マハラノビス距離の等高線をプロットする",
            "text": "ja/step3.md",
            "verify": [
              {
                "name": "このステップには現在、検証はありません",
                "file": "verify3-1.sh",
                "hint": "このステップには現在、検証はありません"
              }
            ]
          },
          {
            "title": "MLE と MCD のマハラノビス距離を比較する",
            "text": "ja/step4.md",
            "verify": [
              {
                "name": "このステップには現在、検証はありません",
                "file": "verify4-1.sh",
                "hint": "このステップには現在、検証はありません"
              }
            ]
          }
        ],
        "intro": {
          "text": "ja/intro.md",
          "title": "はじめに"
        },
        "finish": {
          "text": "ja/finish.md",
          "title": "まとめ"
        }
      }
    },
    {
      "lang": "ru",
      "title": "Робастная оценка ковариации и связь с расстояниями Махаланобиса",
      "description": "В этом практическом занятии мы исследуем применение устойчивой оценки ковариации с использованием расстояний Махаланобиса для данных, распределенных по Гауссу. Расстояние Махаланобиса - это мера расстояния между точкой и распределением. Оно определяется как расстояние между точкой и средним значением распределения, масштабированное обратной матрицей ковариации распределения. Для данных, распределенных по Гауссу, расстояние Махаланобиса можно использовать для вычисления расстояния наблюдения до моды распределения. Мы сравним производительность оценщика минимального определителя ковариации (MCD), устойчивого оценщика ковариации, с стандартным максимальным правдоподобием оценщиком ковариации (MLE) при вычислении расстояний Махаланобиса для зашумленного набора данных.",
      "meta": {
        "title": "Робастная оценка ковариации | Расстояние Махаланобиса | Гауссовы данные",
        "description": "Исследуйте устойчивую оценку ковариации с использованием расстояния Махаланобиса для Гауссовых распределенных данных, сравните оценщики MCD и MLE для зашумленных наборов данных.",
        "keywords": "Робастная оценка ковариации, Расстояние Махаланобиса, Гауссовы данные, Оценщик MCD, Оценщик MLE"
      },
      "details": {
        "steps": [
          {
            "title": "Сгенерировать данные",
            "text": "ru/step1.md",
            "verify": [
              {
                "name": "На данный момент эта стадия не имеет проверки",
                "file": "verify1-1.sh",
                "hint": "На данный момент эта стадия не имеет проверки"
              }
            ]
          },
          {
            "title": "Подгонка оценщиков ковариации MCD и MLE к данным",
            "text": "ru/step2.md",
            "verify": [
              {
                "name": "На данный момент эта стадия не имеет проверки",
                "file": "verify2-1.sh",
                "hint": "На данный момент эта стадия не имеет проверки"
              }
            ]
          },
          {
            "title": "Построить контуру расстояний Махаланобиса",
            "text": "ru/step3.md",
            "verify": [
              {
                "name": "На данный момент эта стадия не имеет проверки",
                "file": "verify3-1.sh",
                "hint": "На данный момент эта стадия не имеет проверки"
              }
            ]
          },
          {
            "title": "Сравнить расстояния Махаланобиса MLE и MCD",
            "text": "ru/step4.md",
            "verify": [
              {
                "name": "На данный момент эта стадия не имеет проверки",
                "file": "verify4-1.sh",
                "hint": "На данный момент эта стадия не имеет проверки"
              }
            ]
          }
        ],
        "intro": {
          "text": "ru/intro.md",
          "title": "Введение"
        },
        "finish": {
          "text": "ru/finish.md",
          "title": "Резюме"
        }
      }
    }
  ]
}
