{
  "$schema": "https://cdn.jsdelivr.net/gh/labex-labs/schema/index.json",
  "type": "lab",
  "title": "Create Packed Bubble Charts with Python",
  "description": "In this lab, we will learn how to create a packed-bubble chart using Matplotlib in Python. The packed-bubble chart is a type of chart that displays data in bubbles of different sizes, with the bubble's size representing the data's magnitude. This chart is useful for displaying scalar data, where the data is a single numeric value associated with an item.",
  "meta": {
    "title": "Packed-Bubble Chart | Python Visualization | Data Visualization",
    "description": "Learn how to create a packed-bubble chart using Matplotlib in Python, a powerful data visualization tool for displaying scalar data.",
    "keywords": "packed-bubble chart, python, matplotlib, data visualization, scalar data"
  },
  "difficulty": "Beginner",
  "time": 30,
  "hidden": true,
  "fee_type": "free",
  "show_in_tutorial": true,
  "details": {
    "steps": [
      {
        "title": "Import Required Libraries",
        "text": "en/step1.md",
        "verify": [
          {
            "name": "This step has no verification at the moment",
            "file": "verify1-1.sh",
            "hint": "This step has no verification at the moment"
          }
        ],
        "skills": [
          "matplotlib/figures_axes",
          "matplotlib/importing_matplotlib",
          "python/data_visualization",
          "python/importing_modules",
          "python/numerical_computing"
        ]
      },
      {
        "title": "Define Data",
        "text": "en/step2.md",
        "verify": [
          {
            "name": "This step has no verification at the moment",
            "file": "verify2-1.sh",
            "hint": "This step has no verification at the moment"
          }
        ],
        "skills": ["python/comments", "python/dictionaries", "python/lists"]
      },
      {
        "title": "Define BubbleChart Class",
        "text": "en/step3.md",
        "verify": [
          {
            "name": "This step has no verification at the moment",
            "file": "verify3-1.sh",
            "hint": "This step has no verification at the moment"
          }
        ],
        "skills": [
          "python/build_in_functions",
          "python/classes_objects",
          "python/comments",
          "python/constructor",
          "python/default_arguments",
          "python/encapsulation",
          "python/for_loops",
          "python/function_definition",
          "python/lists",
          "python/numeric_types",
          "python/polymorphism",
          "python/tuples",
          "python/variables_data_types"
        ]
      },
      {
        "title": "Define Bubble Movement Methods",
        "text": "en/step4.md",
        "verify": [
          {
            "name": "This step has no verification at the moment",
            "file": "verify4-1.sh",
            "hint": "This step has no verification at the moment"
          }
        ],
        "skills": [
          "python/build_in_functions",
          "python/encapsulation",
          "python/function_definition",
          "python/lists",
          "python/tuples"
        ]
      },
      {
        "title": "Define Bubble Collision Method",
        "text": "en/step5.md",
        "verify": [
          {
            "name": "This step has no verification at the moment",
            "file": "verify5-1.sh",
            "hint": "This step has no verification at the moment"
          }
        ],
        "skills": [
          "matplotlib/figures_axes",
          "python/build_in_functions",
          "python/catching_exceptions",
          "python/comments",
          "python/conditional_statements",
          "python/data_collections",
          "python/data_visualization",
          "python/default_arguments",
          "python/encapsulation",
          "python/for_loops",
          "python/function_definition",
          "python/lists",
          "python/numeric_types",
          "python/tuples",
          "python/variables_data_types",
          "python/with_statement"
        ]
      },
      {
        "title": "Create BubbleChart Object and Plot Chart",
        "text": "en/step6.md",
        "verify": [
          {
            "name": "This step has no verification at the moment",
            "file": "verify6-1.sh",
            "hint": "This step has no verification at the moment"
          }
        ],
        "skills": [
          "matplotlib/line_plots",
          "python/build_in_functions",
          "python/data_collections",
          "python/lists",
          "python/tuples",
          "python/variables_data_types"
        ]
      }
    ],
    "intro": {
      "text": "en/intro.md",
      "title": "Introduction",
      "background": "setup.sh"
    },
    "finish": {
      "text": "en/finish.md",
      "title": "Summary"
    },
    "assets": {
      "host01": [
        {
          "file": "packed-bubbles.ipynb",
          "target": "/home/labex/project",
          "chmod": "ugo+rwx"
        }
      ]
    }
  },
  "backend": {
    "imageid": "jupyter-ubuntu:2204"
  },
  "contributors": [],
  "license": {
    "name": "BSD 3-Clause",
    "url": "https://github.com/matplotlib/matplotlib/tree/main/LICENSE",
    "repo": "https://github.com/matplotlib/matplotlib"
  },
  "i18n": [
    {
      "lang": "zh",
      "title": "使用 Python 创建填充气泡图",
      "description": "在本实验中，我们将学习如何使用 Python 中的 Matplotlib 创建填充气泡图。填充气泡图是一种以不同大小的气泡显示数据的图表类型，气泡的大小代表数据的量级。此图表对于显示标量数据很有用，其中数据是与某个项目相关联的单个数值。",
      "meta": {
        "title": "填充气泡图 | Python 可视化 | 数据可视化",
        "description": "学习如何使用 Python 中的 Matplotlib 创建填充气泡图，Matplotlib 是一个用于显示标量数据的强大数据可视化工具。",
        "keywords": "填充气泡图，Python, Matplotlib, 数据可视化，标量数据"
      },
      "details": {
        "steps": [
          {
            "title": "导入所需的库",
            "text": "zh/step1.md",
            "verify": [
              {
                "name": "此步骤目前没有验证",
                "file": "verify1-1.sh",
                "hint": "此步骤目前没有验证"
              }
            ]
          },
          {
            "title": "定义数据",
            "text": "zh/step2.md",
            "verify": [
              {
                "name": "此步骤目前没有验证",
                "file": "verify2-1.sh",
                "hint": "此步骤目前没有验证"
              }
            ]
          },
          {
            "title": "定义 BubbleChart 类",
            "text": "zh/step3.md",
            "verify": [
              {
                "name": "此步骤目前没有验证",
                "file": "verify3-1.sh",
                "hint": "此步骤目前没有验证"
              }
            ]
          },
          {
            "title": "定义气泡移动方法",
            "text": "zh/step4.md",
            "verify": [
              {
                "name": "此步骤目前没有验证",
                "file": "verify4-1.sh",
                "hint": "此步骤目前没有验证"
              }
            ]
          },
          {
            "title": "定义气泡碰撞方法",
            "text": "zh/step5.md",
            "verify": [
              {
                "name": "此步骤目前没有验证",
                "file": "verify5-1.sh",
                "hint": "此步骤目前没有验证"
              }
            ]
          },
          {
            "title": "创建气泡图对象并绘制图表",
            "text": "zh/step6.md",
            "verify": [
              {
                "name": "此步骤目前没有验证",
                "file": "verify6-1.sh",
                "hint": "此步骤目前没有验证"
              }
            ]
          }
        ],
        "intro": {
          "text": "zh/intro.md",
          "title": "介绍"
        },
        "finish": {
          "text": "zh/finish.md",
          "title": "总结"
        }
      }
    },
    {
      "lang": "es",
      "title": "Crear gráficos de burbujas empaquetadas con Python",
      "description": "En este laboratorio, aprenderemos cómo crear un gráfico de burbujas empaquetadas utilizando Matplotlib en Python. El gráfico de burbujas empaquetadas es un tipo de gráfico que muestra datos en burbujas de diferentes tamaños, donde el tamaño de la burbuja representa la magnitud de los datos. Este gráfico es útil para mostrar datos escalares, donde los datos son un solo valor numérico asociado con un elemento.",
      "meta": {
        "title": "Gráfico de burbujas empaquetadas | Visualización de datos con Python | Visualización de datos",
        "description": "Aprende cómo crear un gráfico de burbujas empaquetadas utilizando Matplotlib en Python, una herramienta poderosa de visualización de datos para mostrar datos escalares.",
        "keywords": "gráfico de burbujas empaquetadas, python, matplotlib, visualización de datos, datos escalares"
      },
      "details": {
        "steps": [
          {
            "title": "Importar las bibliotecas necesarias",
            "text": "es/step1.md",
            "verify": [
              {
                "name": "Este paso no tiene verificaciones en este momento",
                "file": "verify1-1.sh",
                "hint": "Este paso no tiene verificaciones en este momento"
              }
            ]
          },
          {
            "title": "Definir los datos",
            "text": "es/step2.md",
            "verify": [
              {
                "name": "Este paso no tiene verificaciones en este momento",
                "file": "verify2-1.sh",
                "hint": "Este paso no tiene verificaciones en este momento"
              }
            ]
          },
          {
            "title": "Definir la clase BubbleChart",
            "text": "es/step3.md",
            "verify": [
              {
                "name": "Este paso no tiene verificaciones en este momento",
                "file": "verify3-1.sh",
                "hint": "Este paso no tiene verificaciones en este momento"
              }
            ]
          },
          {
            "title": "Definir los métodos de movimiento de las burbujas",
            "text": "es/step4.md",
            "verify": [
              {
                "name": "Este paso no tiene verificaciones en este momento",
                "file": "verify4-1.sh",
                "hint": "Este paso no tiene verificaciones en este momento"
              }
            ]
          },
          {
            "title": "Definir el método de colisión de burbujas",
            "text": "es/step5.md",
            "verify": [
              {
                "name": "Este paso no tiene verificaciones en este momento",
                "file": "verify5-1.sh",
                "hint": "Este paso no tiene verificaciones en este momento"
              }
            ]
          },
          {
            "title": "Crear un objeto BubbleChart y trazar el gráfico",
            "text": "es/step6.md",
            "verify": [
              {
                "name": "Este paso no tiene verificaciones en este momento",
                "file": "verify6-1.sh",
                "hint": "Este paso no tiene verificaciones en este momento"
              }
            ]
          }
        ],
        "intro": {
          "text": "es/intro.md",
          "title": "Introducción"
        },
        "finish": {
          "text": "es/finish.md",
          "title": "Resumen"
        }
      }
    },
    {
      "lang": "fr",
      "title": "Créer des graphiques à bulles empaquetées avec Python",
      "description": "Dans ce laboratoire, nous allons apprendre à créer un graphique à bulles empaquetées à l'aide de Matplotlib en Python. Le graphique à bulles empaquetées est un type de graphique qui affiche des données dans des bulles de différentes tailles, la taille de la bulle représentant l'amplitude des données. Ce graphique est utile pour afficher des données scalaires, où les données sont une seule valeur numérique associée à un élément.",
      "meta": {
        "title": "Graphique à bulles empaquetées | Visualisation Python | Visualisation de données",
        "description": "Découvrez comment créer un graphique à bulles empaquetées à l'aide de Matplotlib en Python, un puissant outil de visualisation de données pour afficher des données scalaires.",
        "keywords": "graphique à bulles empaquetées, python, matplotlib, visualisation de données, données scalaires"
      },
      "details": {
        "steps": [
          {
            "title": "Importer les bibliothèques requises",
            "text": "fr/step1.md",
            "verify": [
              {
                "name": "Cette étape n'a pas de vérification pour le moment",
                "file": "verify1-1.sh",
                "hint": "Cette étape n'a pas de vérification pour le moment"
              }
            ]
          },
          {
            "title": "Définir les données",
            "text": "fr/step2.md",
            "verify": [
              {
                "name": "Cette étape n'a pas de vérification pour le moment",
                "file": "verify2-1.sh",
                "hint": "Cette étape n'a pas de vérification pour le moment"
              }
            ]
          },
          {
            "title": "Définir la classe BubbleChart",
            "text": "fr/step3.md",
            "verify": [
              {
                "name": "Cette étape n'a pas de vérification pour le moment",
                "file": "verify3-1.sh",
                "hint": "Cette étape n'a pas de vérification pour le moment"
              }
            ]
          },
          {
            "title": "Définir les méthodes de mouvement des bulles",
            "text": "fr/step4.md",
            "verify": [
              {
                "name": "Cette étape n'a pas de vérification pour le moment",
                "file": "verify4-1.sh",
                "hint": "Cette étape n'a pas de vérification pour le moment"
              }
            ]
          },
          {
            "title": "Définir la méthode de collision des bulles",
            "text": "fr/step5.md",
            "verify": [
              {
                "name": "Cette étape n'a pas de vérification pour le moment",
                "file": "verify5-1.sh",
                "hint": "Cette étape n'a pas de vérification pour le moment"
              }
            ]
          },
          {
            "title": "Créer un objet BubbleChart et tracer le graphique",
            "text": "fr/step6.md",
            "verify": [
              {
                "name": "Cette étape n'a pas de vérification pour le moment",
                "file": "verify6-1.sh",
                "hint": "Cette étape n'a pas de vérification pour le moment"
              }
            ]
          }
        ],
        "intro": {
          "text": "fr/intro.md",
          "title": "Introduction"
        },
        "finish": {
          "text": "fr/finish.md",
          "title": "Résumé"
        }
      }
    },
    {
      "lang": "de",
      "title": "Erstelle gepackte Blasen-Diagramme mit Python",
      "description": "In diesem Lab lernen wir, wie man mit Matplotlib in Python ein gepacktes Blasen-Diagramm erstellt. Das gepackte Blasen-Diagramm ist ein Diagrammtyp, der Daten in Blasen unterschiedlicher Größen darstellt, wobei die Größe der Blase die Größe der Daten repräsentiert. Dieses Diagramm eignet sich zur Darstellung von Skalardaten, wobei die Daten ein einzelner numerischer Wert sind, der einem Element zugeordnet ist.",
      "meta": {
        "title": "Gepacktes Blasen-Diagramm | Python Visualisierung | Datenvisualisierung",
        "description": "Lerne, wie man mit Matplotlib in Python ein gepacktes Blasen-Diagramm erstellt, ein leistungsstarkes Datenvisualisierungstool zur Darstellung von Skalardaten.",
        "keywords": "gepacktes Blasen-Diagramm, Python, Matplotlib, Datenvisualisierung, Skalardaten"
      },
      "details": {
        "steps": [
          {
            "title": "Importiere erforderliche Bibliotheken",
            "text": "de/step1.md",
            "verify": [
              {
                "name": "Dieser Schritt hat momentan keine Verifizierung",
                "file": "verify1-1.sh",
                "hint": "Dieser Schritt hat momentan keine Verifizierung"
              }
            ]
          },
          {
            "title": "Definiere Daten",
            "text": "de/step2.md",
            "verify": [
              {
                "name": "Dieser Schritt hat momentan keine Verifizierung",
                "file": "verify2-1.sh",
                "hint": "Dieser Schritt hat momentan keine Verifizierung"
              }
            ]
          },
          {
            "title": "Definiere die BubbleChart-Klasse",
            "text": "de/step3.md",
            "verify": [
              {
                "name": "Dieser Schritt hat momentan keine Verifizierung",
                "file": "verify3-1.sh",
                "hint": "Dieser Schritt hat momentan keine Verifizierung"
              }
            ]
          },
          {
            "title": "Definiere Blasenbewegungs-Methoden",
            "text": "de/step4.md",
            "verify": [
              {
                "name": "Dieser Schritt hat momentan keine Verifizierung",
                "file": "verify4-1.sh",
                "hint": "Dieser Schritt hat momentan keine Verifizierung"
              }
            ]
          },
          {
            "title": "Definiere die Blasen-Kollisions-Methode",
            "text": "de/step5.md",
            "verify": [
              {
                "name": "Dieser Schritt hat momentan keine Verifizierung",
                "file": "verify5-1.sh",
                "hint": "Dieser Schritt hat momentan keine Verifizierung"
              }
            ]
          },
          {
            "title": "Erstelle ein BubbleChart-Objekt und zeichne den Graphen",
            "text": "de/step6.md",
            "verify": [
              {
                "name": "Dieser Schritt hat momentan keine Verifizierung",
                "file": "verify6-1.sh",
                "hint": "Dieser Schritt hat momentan keine Verifizierung"
              }
            ]
          }
        ],
        "intro": {
          "text": "de/intro.md",
          "title": "Einführung"
        },
        "finish": {
          "text": "de/finish.md",
          "title": "Zusammenfassung"
        }
      }
    },
    {
      "lang": "ja",
      "title": "Python でパックドバブルチャートを作成する",
      "description": "この実験では、Python の Matplotlib を使ってパックドバブルチャートを作成する方法を学びます。パックドバブルチャートは、異なるサイズのバブルでデータを表示するチャートの一種で、バブルのサイズがデータの大きさを表します。このチャートは、データが項目に関連付けられた単一の数値であるスカラーデータを表示するのに便利です。",
      "meta": {
        "title": "パックドバブルチャート | Python 可視化 | データ可視化",
        "description": "Python の強力なデータ可視化ツールである Matplotlib を使ってパックドバブルチャートを作成する方法を学びましょう。スカラーデータを表示するためのデータ可視化ツールです。",
        "keywords": "パックドバブルチャート，python, matplotlib, データ可視化，スカラーデータ"
      },
      "details": {
        "steps": [
          {
            "title": "必要なライブラリをインポートする",
            "text": "ja/step1.md",
            "verify": [
              {
                "name": "このステップには現在、検証はありません",
                "file": "verify1-1.sh",
                "hint": "このステップには現在、検証はありません"
              }
            ]
          },
          {
            "title": "データを定義する",
            "text": "ja/step2.md",
            "verify": [
              {
                "name": "このステップには現在、検証はありません",
                "file": "verify2-1.sh",
                "hint": "このステップには現在、検証はありません"
              }
            ]
          },
          {
            "title": "BubbleChart クラスを定義する",
            "text": "ja/step3.md",
            "verify": [
              {
                "name": "このステップには現在、検証はありません",
                "file": "verify3-1.sh",
                "hint": "このステップには現在、検証はありません"
              }
            ]
          },
          {
            "title": "バブルの移動方法を定義する",
            "text": "ja/step4.md",
            "verify": [
              {
                "name": "このステップには現在、検証はありません",
                "file": "verify4-1.sh",
                "hint": "このステップには現在、検証はありません"
              }
            ]
          },
          {
            "title": "バブルの衝突方法を定義する",
            "text": "ja/step5.md",
            "verify": [
              {
                "name": "このステップには現在、検証はありません",
                "file": "verify5-1.sh",
                "hint": "このステップには現在、検証はありません"
              }
            ]
          },
          {
            "title": "BubbleChart オブジェクトを作成してグラフをプロットする",
            "text": "ja/step6.md",
            "verify": [
              {
                "name": "このステップには現在、検証はありません",
                "file": "verify6-1.sh",
                "hint": "このステップには現在、検証はありません"
              }
            ]
          }
        ],
        "intro": {
          "text": "ja/intro.md",
          "title": "はじめに"
        },
        "finish": {
          "text": "ja/finish.md",
          "title": "まとめ"
        }
      }
    },
    {
      "lang": "ru",
      "title": "Создайте графики с упакованными пузырьками с помощью Python",
      "description": "В этом практическом занятии мы узнаем, как создать график с упакованными пузырьками с использованием Matplotlib в Python. График с упакованными пузырьками - это тип графика, который отображает данные в виде пузырьков разного размера, при этом размер пузырька представляет величину данных. Этот график полезен для отображения скалярных данных, где данные - это одно числовое значение, связанное с элементом.",
      "meta": {
        "title": "График с упакованными пузырьками | Визуализация на Python | Визуализация данных",
        "description": "Изучите, как создать график с упакованными пузырьками с использованием Matplotlib в Python, мощного инструмента визуализации данных для отображения скалярных данных.",
        "keywords": "график с упакованными пузырьками, python, matplotlib, визуализация данных, скалярные данные"
      },
      "details": {
        "steps": [
          {
            "title": "Импортировать необходимые библиотеки",
            "text": "ru/step1.md",
            "verify": [
              {
                "name": "На данный момент эта стадия не имеет проверки",
                "file": "verify1-1.sh",
                "hint": "На данный момент эта стадия не имеет проверки"
              }
            ]
          },
          {
            "title": "Определить данные",
            "text": "ru/step2.md",
            "verify": [
              {
                "name": "На данный момент эта стадия не имеет проверки",
                "file": "verify2-1.sh",
                "hint": "На данный момент эта стадия не имеет проверки"
              }
            ]
          },
          {
            "title": "Определить класс BubbleChart",
            "text": "ru/step3.md",
            "verify": [
              {
                "name": "На данный момент эта стадия не имеет проверки",
                "file": "verify3-1.sh",
                "hint": "На данный момент эта стадия не имеет проверки"
              }
            ]
          },
          {
            "title": "Определить методы движения пузырьков",
            "text": "ru/step4.md",
            "verify": [
              {
                "name": "На данный момент эта стадия не имеет проверки",
                "file": "verify4-1.sh",
                "hint": "На данный момент эта стадия не имеет проверки"
              }
            ]
          },
          {
            "title": "Определить метод столкновения пузырьков",
            "text": "ru/step5.md",
            "verify": [
              {
                "name": "На данный момент эта стадия не имеет проверки",
                "file": "verify5-1.sh",
                "hint": "На данный момент эта стадия не имеет проверки"
              }
            ]
          },
          {
            "title": "Создать объект BubbleChart и построить график",
            "text": "ru/step6.md",
            "verify": [
              {
                "name": "На данный момент эта стадия не имеет проверки",
                "file": "verify6-1.sh",
                "hint": "На данный момент эта стадия не имеет проверки"
              }
            ]
          }
        ],
        "intro": {
          "text": "ru/intro.md",
          "title": "Введение"
        },
        "finish": {
          "text": "ru/finish.md",
          "title": "Резюме"
        }
      }
    },
    {
      "lang": "ko",
      "title": "Python 으로 패킹된 버블 차트 만들기",
      "description": "이 랩에서는 Python 의 Matplotlib 을 사용하여 패킹된 버블 차트를 만드는 방법을 배웁니다. 패킹된 버블 차트는 서로 다른 크기의 버블로 데이터를 표시하는 차트 유형으로, 버블의 크기는 데이터의 크기를 나타냅니다. 이 차트는 항목과 관련된 단일 숫자 값인 스칼라 데이터를 표시하는 데 유용합니다.",
      "meta": {
        "title": "패킹 버블 차트 | Python 시각화 | 데이터 시각화",
        "description": "Python 의 강력한 데이터 시각화 도구인 Matplotlib 을 사용하여 스칼라 데이터를 표시하는 패킹된 버블 차트를 만드는 방법을 알아보세요.",
        "keywords": "패킹 버블 차트, 파이썬, matplotlib, 데이터 시각화, 스칼라 데이터, 버블 차트, Python 차트"
      },
      "details": {
        "steps": [
          {
            "title": "필요한 라이브러리 가져오기",
            "text": "ko/step1.md",
            "verify": [
              {
                "name": "현재 이 단계에는 검증이 없습니다.",
                "file": "verify1-1.sh",
                "hint": "현재 이 단계에는 검증이 없습니다."
              }
            ]
          },
          {
            "title": "데이터 정의",
            "text": "ko/step2.md",
            "verify": [
              {
                "name": "현재 이 단계에는 검증이 없습니다.",
                "file": "verify2-1.sh",
                "hint": "현재 이 단계에는 검증이 없습니다."
              }
            ]
          },
          {
            "title": "BubbleChart 클래스 정의",
            "text": "ko/step3.md",
            "verify": [
              {
                "name": "현재 이 단계에는 검증이 없습니다.",
                "file": "verify3-1.sh",
                "hint": "현재 이 단계에는 검증이 없습니다."
              }
            ]
          },
          {
            "title": "버블 이동 메서드 정의",
            "text": "ko/step4.md",
            "verify": [
              {
                "name": "현재 이 단계에는 검증이 없습니다.",
                "file": "verify4-1.sh",
                "hint": "현재 이 단계에는 검증이 없습니다."
              }
            ]
          },
          {
            "title": "버블 충돌 메서드 정의",
            "text": "ko/step5.md",
            "verify": [
              {
                "name": "현재 이 단계에는 검증이 없습니다.",
                "file": "verify5-1.sh",
                "hint": "현재 이 단계에는 검증이 없습니다."
              }
            ]
          },
          {
            "title": "BubbleChart 객체 생성 및 차트 플롯",
            "text": "ko/step6.md",
            "verify": [
              {
                "name": "현재 이 단계에는 검증이 없습니다.",
                "file": "verify6-1.sh",
                "hint": "현재 이 단계에는 검증이 없습니다."
              }
            ]
          }
        ],
        "intro": {
          "text": "ko/intro.md",
          "title": "소개"
        },
        "finish": {
          "text": "ko/finish.md",
          "title": "요약"
        }
      }
    },
    {
      "lang": "pt",
      "title": "Criar Gráficos de Bolhas Empacotadas com Python",
      "description": "Neste laboratório, aprenderemos como criar um gráfico de bolhas empacotadas usando Matplotlib em Python. O gráfico de bolhas empacotadas é um tipo de gráfico que exibe dados em bolhas de diferentes tamanhos, com o tamanho da bolha representando a magnitude dos dados. Este gráfico é útil para exibir dados escalares, onde os dados são um único valor numérico associado a um item.",
      "meta": {
        "title": "Gráfico de Bolhas Empacotadas | Visualização em Python | Visualização de Dados",
        "description": "Aprenda como criar um gráfico de bolhas empacotadas usando Matplotlib em Python, uma poderosa ferramenta de visualização de dados para exibir dados escalares.",
        "keywords": "gráfico de bolhas empacotadas, python, matplotlib, visualização de dados, dados escalares"
      },
      "details": {
        "steps": [
          {
            "title": "Importar as Bibliotecas Necessárias",
            "text": "pt/step1.md",
            "verify": [
              {
                "name": "Esta etapa não possui verificação no momento",
                "file": "verify1-1.sh",
                "hint": "Esta etapa não possui verificação no momento"
              }
            ]
          },
          {
            "title": "Definir os Dados",
            "text": "pt/step2.md",
            "verify": [
              {
                "name": "Esta etapa não possui verificação no momento",
                "file": "verify2-1.sh",
                "hint": "Esta etapa não possui verificação no momento"
              }
            ]
          },
          {
            "title": "Definir a Classe BubbleChart",
            "text": "pt/step3.md",
            "verify": [
              {
                "name": "Esta etapa não possui verificação no momento",
                "file": "verify3-1.sh",
                "hint": "Esta etapa não possui verificação no momento"
              }
            ]
          },
          {
            "title": "Definir Métodos de Movimento da Bolha",
            "text": "pt/step4.md",
            "verify": [
              {
                "name": "Esta etapa não possui verificação no momento",
                "file": "verify4-1.sh",
                "hint": "Esta etapa não possui verificação no momento"
              }
            ]
          },
          {
            "title": "Definir o Método de Colisão da Bolha",
            "text": "pt/step5.md",
            "verify": [
              {
                "name": "Esta etapa não possui verificação no momento",
                "file": "verify5-1.sh",
                "hint": "Esta etapa não possui verificação no momento"
              }
            ]
          },
          {
            "title": "Criar Objeto BubbleChart e Plotar o Gráfico",
            "text": "pt/step6.md",
            "verify": [
              {
                "name": "Esta etapa não possui verificação no momento",
                "file": "verify6-1.sh",
                "hint": "Esta etapa não possui verificação no momento"
              }
            ]
          }
        ],
        "intro": {
          "text": "pt/intro.md",
          "title": "Introdução"
        },
        "finish": {
          "text": "pt/finish.md",
          "title": "Resumo"
        }
      }
    }
  ]
}
