{
  "$schema": "https://cdn.jsdelivr.net/gh/labex-labs/schema/index.json",
  "type": "challenge",
  "title": "Initialize List with Range | Challenge",
  "description": "In Python, you can create a list of numbers using the range() function. However, sometimes you may want to create a list of numbers that are not sequential or that start at a different number than 0. In such cases, you can use the initialize_list_with_range() function.",
  "meta": {
    "title": "Mastering Python List Creation with Range",
    "description": "Learn how to initialize a list with a custom range and step in Python.",
    "keywords": "python, list, tutorial, range, programming"
  },
  "difficulty": "Beginner",
  "time": 15,
  "hidden": true,
  "fee_type": "free",
  "show_in_tutorial": false,
  "details": {
    "steps": [
      {
        "title": "Initialize List with Range",
        "text": "en/step1.md",
        "verify": [
          {
            "name": "Verify Initialize List with Range",
            "file": "verify1-1.sh",
            "hint": "Please make sure you have completed the required actions.",
            "timeout": 0,
            "showstderr": true
          }
        ],
        "skills": [
          "python/build_in_functions",
          "python/comments",
          "python/data_collections",
          "python/default_arguments",
          "python/function_definition",
          "python/lists",
          "python/tuples",
          "python/variables_data_types"
        ],
        "solutions": ["initialize_list_with_range.py"]
      }
    ],
    "intro": {
      "text": "en/intro.md",
      "background": "setup.sh"
    },
    "finish": {
      "text": "en/finish.md"
    },
    "assets": {
      "host01": [
        {
          "file": "test_initialize_list_with_range.py",
          "target": "/tmp",
          "chmod": "ugo+rwx"
        },
        {
          "file": "initialize_list_with_range.py",
          "target": "/home/labex/project",
          "chmod": "ugo+rwx"
        }
      ]
    }
  },
  "backend": {
    "imageid": "webide-ubuntu:2204"
  },
  "contributors": ["huduo0812", "jiaosenvip"],
  "license": {
    "name": "CC-BY-4.0",
    "url": "https://github.com/30-seconds/30-seconds-of-python/blob/master/LICENSE",
    "repo": "https://github.com/30-seconds/30-seconds-of-python"
  },
  "i18n": [
    {
      "lang": "zh",
      "title": "使用范围初始化列表 | 挑战",
      "description": "在Python中，你可以使用range()函数创建一个数字列表。然而，有时你可能想要创建一个非连续的数字列表，或者从不同于0的数字开始的列表。在这种情况下，你可以使用initialize_list_with_range()函数。",
      "meta": {
        "title": "掌握使用范围创建Python列表",
        "description": "学习如何在Python中使用自定义范围和步长初始化列表。",
        "keywords": "Python, 列表, 教程, 范围, 编程"
      },
      "details": {
        "steps": [
          {
            "title": "使用范围初始化列表",
            "text": "zh/step1.md",
            "verify": [
              {
                "name": "验证使用范围初始化列表",
                "file": "verify1-1.sh",
                "hint": "请确保你已完成所需操作。"
              }
            ],
            "solutions": ["initialize_list_with_range.py"]
          }
        ],
        "intro": {
          "text": "zh/intro.md",
          "title": "介绍"
        },
        "finish": {
          "text": "zh/finish.md",
          "title": "总结"
        }
      }
    }
  ]
}
