{
  "type": "lab",
  "difficulty": "Beginner",
  "time": 20,
  "hidden": false,
  "fee_type": "free",
  "show_in_tutorial": true,
  "backend": {
    "imageid": "jupyter-ubuntu:2204"
  },
  "contributors": ["huduo0812"],
  "license": {
    "name": "BSD 3-Clause",
    "url": "https://github.com/matplotlib/matplotlib/tree/main/LICENSE",
    "repo": "https://github.com/matplotlib/matplotlib"
  },
  "assets": {
    "host01": [
      {
        "file": "color-by-yvalue.ipynb",
        "target": "/home/labex/project",
        "chmod": "ugo+rwx"
      }
    ]
  },
  "i18n": [
    {
      "lang": "en",
      "title": "Color by Y-Value",
      "description": "Matplotlib is a data visualization library in Python. It is a powerful tool for creating a wide range of graphs and charts. One of the features of Matplotlib is the ability to plot lines with different colors based on the y-value. This lab will demonstrate how to use masked arrays to plot a line with different colors by y-value.",
      "meta": {
        "title": "Plotting Lines with Different Colors by Y-Value",
        "description": "Learn how to use Matplotlib in Python to plot lines with different colors based on the y-value.",
        "keywords": "matplotlib, python, line plot, color by y value, data visualization"
      },
      "details": {
        "steps": [
          {
            "title": "Import Required Libraries",
            "text": "en/step1.md",
            "verify": [
              {
                "name": "This step has no verification at the moment",
                "file": "verify1.sh",
                "hint": "This step has no verification at the moment"
              }
            ],
            "skills": [
              "matplotlib/figures_axes",
              "matplotlib/importing_matplotlib",
              "python/data_visualization",
              "python/importing_modules",
              "python/numerical_computing"
            ]
          },
          {
            "title": "Create Data",
            "text": "en/step2.md",
            "verify": [
              {
                "name": "This step has no verification at the moment",
                "file": "verify2.sh",
                "hint": "This step has no verification at the moment"
              }
            ],
            "skills": ["python/tuples"]
          },
          {
            "title": "Create Masked Arrays",
            "text": "en/step3.md",
            "verify": [
              {
                "name": "This step has no verification at the moment",
                "file": "verify3.sh",
                "hint": "This step has no verification at the moment"
              }
            ],
            "skills": ["python/tuples"]
          },
          {
            "title": "Create Plot",
            "text": "en/step4.md",
            "verify": [
              {
                "name": "This step has no verification at the moment",
                "file": "verify4.sh",
                "hint": "This step has no verification at the moment"
              }
            ],
            "skills": ["matplotlib/line_plots", "python/tuples"]
          }
        ],
        "intro": {
          "text": "en/intro.md",
          "background": "setup.sh",
          "title": "Introduction"
        },
        "finish": {
          "text": "en/finish.md",
          "title": "Summary"
        }
      }
    },
    {
      "lang": "zh",
      "title": "按Y值设置颜色",
      "description": "Matplotlib是Python中的一个数据可视化库。它是创建各种图形和图表的强大工具。Matplotlib的功能之一是能够根据y值绘制不同颜色的线条。本实验将演示如何使用掩码数组按y值绘制不同颜色的线条。",
      "meta": {
        "title": "按Y值绘制不同颜色的线条",
        "description": "学习如何在Python中使用Matplotlib根据y值绘制不同颜色的线条。",
        "keywords": "Matplotlib, Python, 折线图, 按y值设置颜色, 数据可视化"
      },
      "details": {
        "steps": [
          {
            "title": "导入所需库",
            "text": "zh/step1.md",
            "verify": [
              {
                "name": "此步骤目前没有验证",
                "file": "verify1.sh",
                "hint": "此步骤目前没有验证"
              }
            ],
            "skills": [
              "matplotlib/figures_axes",
              "matplotlib/importing_matplotlib",
              "python/data_visualization",
              "python/importing_modules",
              "python/numerical_computing"
            ]
          },
          {
            "title": "创建数据",
            "text": "zh/step2.md",
            "verify": [
              {
                "name": "此步骤目前没有验证",
                "file": "verify2.sh",
                "hint": "此步骤目前没有验证"
              }
            ],
            "skills": ["python/tuples"]
          },
          {
            "title": "创建掩码数组",
            "text": "zh/step3.md",
            "verify": [
              {
                "name": "此步骤目前没有验证",
                "file": "verify3.sh",
                "hint": "此步骤目前没有验证"
              }
            ],
            "skills": ["python/tuples"]
          },
          {
            "title": "创建图表",
            "text": "zh/step4.md",
            "verify": [
              {
                "name": "此步骤目前没有验证",
                "file": "verify4.sh",
                "hint": "此步骤目前没有验证"
              }
            ],
            "skills": ["matplotlib/line_plots", "python/tuples"]
          }
        ],
        "intro": {
          "text": "zh/intro.md",
          "background": "setup.sh",
          "title": "介绍"
        },
        "finish": {
          "text": "zh/finish.md",
          "title": "总结"
        }
      }
    }
  ]
}
