{
  "$schema": "https://cdn.jsdelivr.net/gh/labex-labs/schema/index.json",
  "type": "lab",
  "title": "Find All Matching Indexes",
  "description": "In this lab, you will learn how to use the `enumerate()` function and list comprehension in Python to find the indexes of all elements in a list that satisfy a given testing function.",
  "meta": {
    "title": "Python | List Comprehension | Enumerate Function",
    "description": "Learn how to use Python's enumerate() function and list comprehension to find the indexes of all elements in a list that satisfy a given testing function.",
    "keywords": "Python, List Comprehension, Enumerate Function, Index, Filtering"
  },
  "difficulty": "Beginner",
  "time": 15,
  "hidden": true,
  "fee_type": "free",
  "show_in_tutorial": true,
  "details": {
    "steps": [
      {
        "title": "Find All Matching Indexes",
        "text": "en/step1.md",
        "verify": [
          {
            "name": "Verify Find Index of All",
            "file": "verify1-1.sh",
            "hint": "Please make sure you have completed the required actions.",
            "timeout": 0,
            "showstderr": true
          }
        ],
        "skills": [
          "python/build_in_functions",
          "python/comments",
          "python/conditional_statements",
          "python/for_loops",
          "python/function_definition",
          "python/lambda_functions",
          "python/list_comprehensions",
          "python/lists",
          "python/tuples"
        ]
      }
    ],
    "intro": {
      "text": "en/intro.md",
      "title": "Introduction",
      "background": "setup.sh"
    },
    "finish": {
      "text": "en/finish.md",
      "title": "Summary"
    },
    "assets": {
      "host01": [
        {
          "file": "test_find_index_of_all.py",
          "target": "/tmp",
          "chmod": "ugo+rwx"
        },
        {
          "file": "find_index_of_all.py",
          "target": "/home/labex/project",
          "chmod": "ugo+rwx"
        }
      ]
    }
  },
  "backend": {
    "imageid": "webide-ubuntu:2204"
  },
  "contributors": ["huduo0812", "jiaosenvip"],
  "license": {
    "name": "CC-BY-4.0",
    "url": "https://github.com/30-seconds/30-seconds-of-python/blob/master/LICENSE",
    "repo": "https://github.com/30-seconds/30-seconds-of-python"
  },
  "i18n": [
    {
      "lang": "zh",
      "title": "找到所有匹配的索引",
      "description": "在这个实验中，你将学习如何在 Python 中使用 `enumerate()` 函数和列表推导式来找到列表中所有满足给定测试函数的元素的索引。",
      "meta": {
        "title": "Python | 列表推导式 | 枚举函数",
        "description": "学习如何使用 Python 的枚举函数和列表推导式来找到列表中所有满足给定测试函数的元素的索引。",
        "keywords": "Python, 列表推导式，枚举函数，索引，过滤"
      },
      "details": {
        "steps": [
          {
            "title": "找到所有匹配的索引",
            "text": "zh/step1.md",
            "verify": [
              {
                "name": "验证找到所有索引",
                "file": "verify1-1.sh",
                "hint": "请确保你已完成所需操作。"
              }
            ]
          }
        ],
        "intro": {
          "text": "zh/intro.md",
          "title": "介绍"
        },
        "finish": {
          "text": "zh/finish.md",
          "title": "总结"
        }
      }
    },
    {
      "lang": "es",
      "title": "Encuentra todos los índices coincidentes",
      "description": "En este laboratorio, aprenderás a usar la función `enumerate()` y la comprensión de listas en Python para encontrar los índices de todos los elementos en una lista que cumplen una función de prueba dada.",
      "meta": {
        "title": "Python | Comprensión de listas | Función Enumerate",
        "description": "Aprende a usar la función enumerate() de Python y la comprensión de listas para encontrar los índices de todos los elementos en una lista que cumplen una función de prueba dada.",
        "keywords": "Python, Comprensión de listas, Función Enumerate, Índice, Filtrado"
      },
      "details": {
        "steps": [
          {
            "title": "Encuentra todos los índices coincidentes",
            "text": "es/step1.md",
            "verify": [
              {
                "name": "Verifica Encuentra Índice de Todos",
                "file": "verify1-1.sh",
                "hint": "Asegúrate de haber completado las acciones requeridas."
              }
            ]
          }
        ],
        "intro": {
          "text": "es/intro.md",
          "title": "Introducción"
        },
        "finish": {
          "text": "es/finish.md",
          "title": "Resumen"
        }
      }
    },
    {
      "lang": "fr",
      "title": "Trouver tous les index correspondants",
      "description": "Dans ce laboratoire, vous allez apprendre à utiliser la fonction `enumerate()` et la compréhension de liste en Python pour trouver les index de tous les éléments d'une liste qui satisfont une fonction de test donnée.",
      "meta": {
        "title": "Python | Compréhension de liste | Fonction Enumerate",
        "description": "Découvrez comment utiliser la fonction `enumerate()` et la compréhension de liste de Python pour trouver les index de tous les éléments d'une liste qui satisfont une fonction de test donnée.",
        "keywords": "Python, Compréhension de liste, Fonction Enumerate, Index, Filtrer"
      },
      "details": {
        "steps": [
          {
            "title": "Trouver tous les index correspondants",
            "text": "fr/step1.md",
            "verify": [
              {
                "name": "Vérifier la recherche d'index de tous",
                "file": "verify1-1.sh",
                "hint": "Veuillez vous assurer d'avoir effectué les actions requises."
              }
            ]
          }
        ],
        "intro": {
          "text": "fr/intro.md",
          "title": "Introduction"
        },
        "finish": {
          "text": "fr/finish.md",
          "title": "Résumé"
        }
      }
    },
    {
      "lang": "de",
      "title": "Alle passenden Indizes finden",
      "description": "In diesem Lab werden Sie lernen, wie Sie in Python die `enumerate()`-Funktion und Listenverständnis verwenden, um die Indizes aller Elemente in einer Liste zu finden, die eine gegebene Testfunktion erfüllen.",
      "meta": {
        "title": "Python | Listenverständnis | Enumerate-Funktion",
        "description": "Lernen Sie, wie Sie die `enumerate()`-Funktion und Listenverständnis in Python verwenden, um die Indizes aller Elemente in einer Liste zu finden, die eine gegebene Testfunktion erfüllen.",
        "keywords": "Python, Listenverständnis, Enumerate-Funktion, Index, Filterung"
      },
      "details": {
        "steps": [
          {
            "title": "Alle passenden Indizes finden",
            "text": "de/step1.md",
            "verify": [
              {
                "name": "Verifizieren Sie alle passenden Indizes",
                "file": "verify1-1.sh",
                "hint": "Bitte stellen Sie sicher, dass Sie die erforderlichen Aktionen ausgeführt haben."
              }
            ]
          }
        ],
        "intro": {
          "text": "de/intro.md",
          "title": "Einführung"
        },
        "finish": {
          "text": "de/finish.md",
          "title": "Zusammenfassung"
        }
      }
    },
    {
      "lang": "ja",
      "title": "すべての一致するインデックスを見つける",
      "description": "この実験では、Python の `enumerate()` 関数とリスト内包表記を使って、与えられたテスト関数を満たすリスト内のすべての要素のインデックスを見つける方法を学びます。",
      "meta": {
        "title": "Python | リスト内包表記 | 列挙関数",
        "description": "Python の enumerate() 関数とリスト内包表記を使って、与えられたテスト関数を満たすリスト内のすべての要素のインデックスを見つける方法を学びましょう。",
        "keywords": "Python, リスト内包表記，列挙関数，インデックス，フィルタリング"
      },
      "details": {
        "steps": [
          {
            "title": "すべての一致するインデックスを見つける",
            "text": "ja/step1.md",
            "verify": [
              {
                "name": "すべてのインデックスを見つけることを確認する",
                "file": "verify1-1.sh",
                "hint": "必要な操作を完了していることを確認してください。"
              }
            ]
          }
        ],
        "intro": {
          "text": "ja/intro.md",
          "title": "はじめに"
        },
        "finish": {
          "text": "ja/finish.md",
          "title": "まとめ"
        }
      }
    },
    {
      "lang": "ru",
      "title": "Найти все совпадающие индексы",
      "description": "В этом практическом занятии вы научитесь использовать функцию `enumerate()` и списочное выражение в Python для нахождения индексов всех элементов в списке, которые удовлетворяют заданной тестирующей функции.",
      "meta": {
        "title": "Python | Списочное выражение | Функция enumerate",
        "description": "Изучите, как использовать функцию enumerate() и списочное выражение в Python для нахождения индексов всех элементов в списке, которые удовлетворяют заданной тестирующей функции.",
        "keywords": "Python, Списочное выражение, Функция enumerate, Индекс, Фильтрация"
      },
      "details": {
        "steps": [
          {
            "title": "Найти все совпадающие индексы",
            "text": "ru/step1.md",
            "verify": [
              {
                "name": "Проверить нахождение всех индексов",
                "file": "verify1-1.sh",
                "hint": "Пожалуйста, убедитесь, что вы выполнили все необходимые действия."
              }
            ]
          }
        ],
        "intro": {
          "text": "ru/intro.md",
          "title": "Введение"
        },
        "finish": {
          "text": "ru/finish.md",
          "title": "Резюме"
        }
      }
    }
  ]
}
