{
  "type": "lab",
  "difficulty": "Beginner",
  "time": 30,
  "hidden": false,
  "fee_type": "free",
  "show_in_tutorial": true,
  "backend": {
    "imageid": "jupyter-ubuntu:2204"
  },
  "contributors": [],
  "license": {
    "name": "BSD 3-Clause",
    "url": "https://github.com/scikit-learn/scikit-learn/tree/main/LICENSE",
    "repo": "https://github.com/scikit-learn/scikit-learn"
  },
  "i18n": [
    {
      "lang": "en",
      "title": "Visualize High-Dimensional Data with t-SNE",
      "description": "t-SNE (t-Distributed Stochastic Neighbor Embedding) is a dimensionality reduction technique used for visualizing high-dimensional datasets. This tutorial will guide you through the process of using t-SNE to visualize datasets using Python's scikit-learn library.",
      "meta": {
        "title": "t-SNE Tutorial | Dimensionality Reduction | Data Visualization",
        "description": "Learn how to use t-SNE, a powerful dimensionality reduction technique, to visualize high-dimensional datasets in Python with scikit-learn.",
        "keywords": "t-SNE, dimensionality reduction, data visualization, Python, scikit-learn"
      },
      "details": {
        "steps": [
          {
            "title": "Import Libraries",
            "text": "en/step1.md",
            "verify": [
              {
                "name": "This step has no verification at the moment",
                "file": "verify1.sh",
                "hint": "This step has no verification at the moment"
              }
            ],
            "skills": ["ml/sklearn"]
          },
          {
            "title": "Create Data",
            "text": "en/step2.md",
            "verify": [
              {
                "name": "This step has no verification at the moment",
                "file": "verify2.sh",
                "hint": "This step has no verification at the moment"
              }
            ],
            "skills": ["ml/sklearn"]
          },
          {
            "title": "Visualize Data",
            "text": "en/step3.md",
            "verify": [
              {
                "name": "This step has no verification at the moment",
                "file": "verify3.sh",
                "hint": "This step has no verification at the moment"
              }
            ],
            "skills": ["ml/sklearn"]
          },
          {
            "title": "Apply t-SNE to Data",
            "text": "en/step4.md",
            "verify": [
              {
                "name": "This step has no verification at the moment",
                "file": "verify4.sh",
                "hint": "This step has no verification at the moment"
              }
            ],
            "skills": ["ml/sklearn"]
          },
          {
            "title": "Visualize t-SNE Results",
            "text": "en/step5.md",
            "verify": [
              {
                "name": "This step has no verification at the moment",
                "file": "verify5.sh",
                "hint": "This step has no verification at the moment"
              }
            ],
            "skills": ["ml/sklearn"]
          },
          {
            "title": "Repeat for Other Datasets",
            "text": "en/step6.md",
            "verify": [
              {
                "name": "This step has no verification at the moment",
                "file": "verify6.sh",
                "hint": "This step has no verification at the moment"
              }
            ],
            "skills": ["ml/sklearn"]
          }
        ],
        "intro": {
          "text": "en/intro.md",
          "background": "setup.sh",
          "title": "Introduction"
        },
        "finish": {
          "text": "en/finish.md",
          "title": "Summary"
        }
      }
    },
    {
      "lang": "zh",
      "title": "使用t-SNE可视化高维数据",
      "description": "t-SNE（t-分布随机邻域嵌入）是一种用于可视化高维数据集的降维技术。本教程将指导你使用Python的scikit-learn库，通过t-SNE可视化数据集的过程。",
      "meta": {
        "title": "t-SNE教程 | 降维 | 数据可视化",
        "description": "学习如何使用强大的降维技术t-SNE，在Python中借助scikit-learn可视化高维数据集。",
        "keywords": "t-SNE, 降维, 数据可视化, Python, scikit-learn"
      },
      "details": {
        "steps": [
          {
            "title": "导入库",
            "text": "zh/step1.md",
            "verify": [
              {
                "name": "此步骤目前没有验证",
                "file": "verify1.sh",
                "hint": "此步骤目前没有验证"
              }
            ],
            "skills": ["ml/sklearn"]
          },
          {
            "title": "创建数据",
            "text": "zh/step2.md",
            "verify": [
              {
                "name": "此步骤目前没有验证",
                "file": "verify2.sh",
                "hint": "此步骤目前没有验证"
              }
            ],
            "skills": ["ml/sklearn"]
          },
          {
            "title": "可视化数据",
            "text": "zh/step3.md",
            "verify": [
              {
                "name": "此步骤目前没有验证",
                "file": "verify3.sh",
                "hint": "此步骤目前没有验证"
              }
            ],
            "skills": ["ml/sklearn"]
          },
          {
            "title": "对数据应用t-SNE",
            "text": "zh/step4.md",
            "verify": [
              {
                "name": "此步骤目前没有验证",
                "file": "verify4.sh",
                "hint": "此步骤目前没有验证"
              }
            ],
            "skills": ["ml/sklearn"]
          },
          {
            "title": "可视化t-SNE结果",
            "text": "zh/step5.md",
            "verify": [
              {
                "name": "此步骤目前没有验证",
                "file": "verify5.sh",
                "hint": "此步骤目前没有验证"
              }
            ],
            "skills": ["ml/sklearn"]
          },
          {
            "title": "对其他数据集重复操作",
            "text": "zh/step6.md",
            "verify": [
              {
                "name": "此步骤目前没有验证",
                "file": "verify6.sh",
                "hint": "此步骤目前没有验证"
              }
            ],
            "skills": ["ml/sklearn"]
          }
        ],
        "intro": {
          "text": "zh/intro.md",
          "background": "setup.sh",
          "title": "介绍"
        },
        "finish": {
          "text": "zh/finish.md",
          "title": "总结"
        }
      }
    }
  ],
  "details": {
    "assets": {
      "host01": [
        {
          "file": "plot-t-sne-perplexity.ipynb",
          "target": "/home/labex/project",
          "chmod": "ugo+rwx"
        }
      ]
    }
  }
}
